uo/__init__.py
uo-0.0.6.dist-info/licenses/LICENSE
uo-0.0.6.dist-info/METADATA
uo-0.0.6.dist-info/WHEEL
uo-0.0.6.dist-info/top_level.txt
uo-0.0.6.dist-info/RECORD
