Metadata-Version: 2.4
Name: uo
Version: 0.0.6
Summary: pipeline computing
Home-page: https://github.com/t-c-w/uo
Author: Thor Whalen
License: apache-2.0
Platform: any
License-File: LICENSE
Dynamic: license-file
